blobfish/__init__.py
blobfish/ejbca/__init__.py
blobfish/ejbca/client.py
blobfish_ejbca_client_python-0.1.0.dist-info/METADATA
blobfish_ejbca_client_python-0.1.0.dist-info/WHEEL
blobfish_ejbca_client_python-0.1.0.dist-info/top_level.txt
blobfish_ejbca_client_python-0.1.0.dist-info/RECORD
